drremote/__init__.py
drremote/__main__.py
drremote/drremote.py
drremote/get_resolve.py
drremote/output.py
drremote/parse.py
drremote-0.1.0.6.dist-info/LICENSE
drremote-0.1.0.6.dist-info/METADATA
drremote-0.1.0.6.dist-info/WHEEL
drremote-0.1.0.6.dist-info/entry_points.txt
drremote-0.1.0.6.dist-info/top_level.txt
drremote-0.1.0.6.dist-info/RECORD
