Metadata-Version: 2.1
Name: drremote
Version: 0.1.0.6
Summary: DRRemote is a python modul which offers access to Davinci Resolve Studio.
Home-page: 
Download-URL: https://github.com/sto3014/DRRemote/archive/refs/heads/main.zip
Author: Dieter Stockhausen
Author-email: dieter@schwingenhausen.at
License: MIT
Keywords: python davinci resolve api
License-File: LICENSE
